{
  "model": {
    "category": "CNN",
    "description": "Trained SqueezeNet model on Caffe2",
    "files": {
      "init": {
        "filename": "init_net.pb",
        "location": "https://s3.amazonaws.com/download.caffe2.ai/models/squeezenet/init_net.pb",
        "md5": "a589d31d93c44d353ae2cd92af4d5a3f"
      },
      "predict": {
        "filename": "predict_net.pb",
        "location": "https://s3.amazonaws.com/download.caffe2.ai/models/squeezenet/predict_net.pb",
        "md5": "694bfdd02e9ccb57bfc4acb451fbfb2d"
      }
    },
    "format": "caffe2",
    "kind": "deployment",
    "name": "squeezenet-taskset-f0"
  },
  "tests": [
    {
      "commands": [
        "{program} --net {files.predict} --init_net {files.init} --warmup {warmup} --iter {iter} --input \"data\" --input_dims \"1,3,224,224\" --input_type float --run_individual true"
      ],
      "identifier": "squeezenet-taskset-f0",
      "platform_args": {
        "taskset": "f0"
      },
      "iter": 50,
      "metric": "delay",
      "warmup": 1
    }
  ]
}
